Metadata-Version: 2.1
Name: invalid
Version: 0.0.1
Summary: Simple command line input validator
Home-page: https://github.com/ryan-mooore/invalid
Author: Ryan Moore
License: MIT
Download-URL: https://github.com/ryan-mooore/invalid/archive/refs/tags/v0.0.1.tar.gz
Keywords: cli,input,validation
Platform: UNKNOWN
Classifier: Development Status :: 3 - Alpha
Classifier: Programming Language :: Python :: 3
Classifier: License :: OSI Approved :: MIT License
Classifier: Operating System :: OS Independent
License-File: LICENSE.txt
